{
  "simple_select_authors": {
    "times": [
      19.0692,
      23.0388,
      23.4959,
      28.1456,
      20.4694,
      21.2687,
      20.319,
      21.9161,
      20.693
    ],
    "memories": [
      1508386.8135,
      1508463.1133,
      1508278.0361,
      1508463.3242,
      1508463.0508,
      1508464.2119,
      1508464.1768,
      1508274.6572,
      1508464.1943
    ],
    "output_lengths": [
      5262254,
      5262254,
      5262254,
      5262254,
      5262254,
      5262254,
      5262254,
      5262254,
      5262254
    ]
  },
  "simple_count_posts": {
    "times": [
      7.5961,
      0.6473,
      0.5681,
      0.4715,
      0.5971,
      0.5832,
      0.5819,
      0.5776,
      0.536
    ],
    "memories": [
      25.333,
      35.3242,
      32.0352,
      35.4414,
      35.5117,
      35.5117,
      35.5117,
      32.0479,
      35.5117
    ],
    "output_lengths": [
      1,
      1,
      1,
      1,
      1,
      1,
      1,
      1,
      1
    ]
  },
  "simple_unique_subreddits": {
    "times": [
      48.7414,
      212.2034,
      209.7658,
      192.4794,
      107.9331,
      210.0415,
      209.8995,
      209.7026,
      91.1196
    ],
    "memories": [
      105375.9824,
      105400.0791,
      105397.2822,
      105400.0791,
      105400.0215,
      105400.0088,
      105400.126,
      105397.126,
      105400.0088
    ],
    "output_lengths": [
      489674,
      489674,
      489674,
      489674,
      489674,
      489674,
      489674,
      489674,
      489674
    ]
  },
  "join_posts_with_authors": {
    "times": [
      271.5491,
      318.9373,
      245.5316,
      276.6438,
      266.8058,
      232.3425,
      248.7123,
      236.7416
    ],
    "memories": [
      7977628.7637,
      7977750.3574,
      7977749.042,
      7977750.5684,
      7977750.498,
      7977750.3574,
      7977749.0293,
      7977750.4121
    ],
    "output_lengths": [
      19770699,
      19770699,
      19770699,
      19770699,
      19770699,
      19770699,
      19770699,
      19770699
    ]
  },
  "join_posts_with_subreddits": {
    "times": [
      526.1753,
      634.5769,
      623.401,
      630.0958,
      598.3527,
      557.7757,
      556.3425,
      568.096
    ],
    "memories": [
      7491107.2314,
      7491109.2236,
      7491107.4004,
      7491109.2939,
      7491109.3486,
      7491109.3486,
      7491107.3018,
      7491109.3486
    ],
    "output_lengths": [
      18626302,
      18626302,
      18626302,
      18626302,
      18626302,
      18626302,
      18626302,
      18626302
    ]
  },
  "analytical_top_posts_by_score": {
    "times": [
      12.2854,
      71.8962,
      80.1558,
      43.9285,
      53.0025,
      13.7418,
      10.9808,
      20.6521
    ],
    "memories": [
      30.6523,
      37.082,
      34.2773,
      36.9023,
      36.8711,
      36.8711,
      34.1494,
      36.8135
    ],
    "output_lengths": [
      10,
      10,
      10,
      10,
      10,
      10,
      10,
      10
    ]
  },
  "analytical_average_comments_per_post": {
    "times": [
      8.029,
      8.6526,
      8.389,
      8.5294,
      8.5139,
      8.4984,
      8.656,
      8.5984
    ],
    "memories": [
      25.0859,
      27.0938,
      25.2061,
      26.9717,
      26.9717,
      26.9717,
      25.0781,
      26.9717
    ],
    "output_lengths": [
      1,
      1,
      1,
      1,
      1,
      1,
      1,
      1
    ]
  },
  "analytical_active_subreddits_by_post_count": {
    "times": [
      20.0172,
      23.6913,
      23.5444,
      22.9242,
      22.7418,
      21.4737,
      21.1296,
      21.6844
    ],
    "memories": [
      30.0498,
      31.4326,
      29.8936,
      31.4326,
      31.3623,
      31.3047,
      29.8232,
      31.4326
    ],
    "output_lengths": [
      10,
      10,
      10,
      10,
      10,
      10,
      10,
      10
    ]
  },
  "join_comments_with_posts": {
    "times": [
      264.2715,
      272.2788,
      251.4989,
      265.2234,
      264.3988,
      254.0848,
      266.3161
    ],
    "memories": [
      2976463.0439,
      2976460.916,
      2976462.9424,
      2976463.0205,
      2976463.0205,
      2976460.9736,
      2976463.0752
    ],
    "output_lengths": [
      8716807,
      8716807,
      8716807,
      8716807,
      8716807,
      8716807,
      8716807
    ]
  },
  "nested_top_commenters_on_top_post": {
    "times": [
      19.06,
      17.9873,
      18.095,
      17.95,
      18.0469,
      18.3369,
      18.0847
    ],
    "memories": [
      2037.042,
      2035.2314,
      2037.5283,
      2037.4561,
      2037.4561,
      2035.6514,
      2037.5264
    ],
    "output_lengths": [
      9569,
      9569,
      9569,
      9569,
      9569,
      9569,
      9569
    ]
  },
  "nested_posts_by_most_active_author": {
    "times": [
      29.6098,
      29.1059,
      28.999,
      29.0166,
      29.1372,
      29.5698,
      29.5586
    ],
    "memories": [
      28273.0625,
      28275.4375,
      28272.8984,
      28272.8281,
      28272.8281,
      28275.3799,
      28272.8984
    ],
    "output_lengths": [
      39398,
      39398,
      39398,
      39398,
      39398,
      39398,
      39398
    ]
  },
  "nested_subreddits_with_high_avg_score": {
    "times": [
      35.235,
      150.9777,
      35.5145,
      35.3302,
      35.3088,
      35.3162,
      36.0606,
      35.3638
    ],
    "memories": [
      454.5811,
      40.5508,
      42.1309,
      41.2773,
      40.4336,
      40.5488,
      39.4004,
      40.6191
    ],
    "output_lengths": [
      100,
      100,
      100,
      100,
      100,
      100,
      100,
      100
    ]
  }
}